kubit/__init__.py
kubit-1.3.0.dist-info/METADATA
kubit-1.3.0.dist-info/WHEEL
kubit-1.3.0.dist-info/top_level.txt
kubit-1.3.0.dist-info/RECORD
