Metadata-Version: 2.1
Name: kubit
Version: 1.3.0
Summary: kubit
Home-page: UNKNOWN
Author: Kubit AI, Inc.
Author-email: info@kubit.co
License: MIT License
Platform: UNKNOWN
Requires-Dist: nbformat
Requires-Dist: tornado
Requires-Dist: notebook
